Metadata-Version: 1.0
Name: dlchessrog
Version: 0.0.2
Summary: My chess bot modules
Home-page: UNKNOWN
Author: UNKNOWN
Author-email: UNKNOWN
License: MIT
Platform: UNKNOWN
